esi_ui/__init__.py
esi_ui/api/__init__.py
esi_ui/api/esi_api.py
esi_ui/api/esi_rest_api.py
esi_ui/content/__init__.py
esi_ui/content/baremetal_topology/__init__.py
esi_ui/content/baremetal_topology/panel.py
esi_ui/content/baremetal_topology/urls.py
esi_ui/content/baremetal_topology/views.py
esi_ui/content/baremetal_topology/templates/baremetal_topology/_graph_view.html
esi_ui/content/baremetal_topology/templates/baremetal_topology/_post_massage.html
esi_ui/content/baremetal_topology/templates/baremetal_topology/_svg_element.html
esi_ui/content/baremetal_topology/templates/baremetal_topology/iframe.html
esi_ui/content/baremetal_topology/templates/baremetal_topology/index.html
esi_ui/content/baremetal_topology/templates/baremetal_topology/client_side/_balloon_container.html
esi_ui/content/baremetal_topology/templates/baremetal_topology/client_side/_balloon_device.html
esi_ui/content/baremetal_topology/templates/baremetal_topology/client_side/_balloon_instance.html
esi_ui/content/baremetal_topology/templates/baremetal_topology/client_side/_balloon_net.html
esi_ui/content/baremetal_topology/templates/baremetal_topology/client_side/_balloon_network_port.html
esi_ui/content/baremetal_topology/templates/baremetal_topology/client_side/_balloon_port.html
esi_ui/content/nodes/__init__.py
esi_ui/content/nodes/panel.py
esi_ui/content/nodes/urls.py
esi_ui/content/nodes/views.py
esi_ui/content/nodes/templates/nodes/index.html
esi_ui/content/offers/__init__.py
esi_ui/content/offers/panel.py
esi_ui/content/offers/urls.py
esi_ui/content/offers/views.py
esi_ui/content/offers/templates/offers/index.html
esi_ui/enabled/_6000_esi_panel_group.py
esi_ui/enabled/_6010_project_nodes_panel.py
esi_ui/enabled/_6020_project_offers_panel.py
esi_ui/enabled/_6030_project_network_topology_panel.py
esi_ui/static/dashboard/project/esi/esi.module.js
esi_ui/static/dashboard/project/esi/nodes.html
esi_ui/static/dashboard/project/esi/offers.html
esi_ui-0.1.0.dist-info/AUTHORS
esi_ui-0.1.0.dist-info/LICENSE
esi_ui-0.1.0.dist-info/METADATA
esi_ui-0.1.0.dist-info/WHEEL
esi_ui-0.1.0.dist-info/pbr.json
esi_ui-0.1.0.dist-info/top_level.txt
esi_ui-0.1.0.dist-info/RECORD
