Metadata-Version: 2.1
Name: esi-ui
Version: 0.1.0
Summary: A panel plugin for OpenStack Dashboard
Home-page: https://github.com/CCI-MOC/esi-ui.git
Author: Austin Jamias
Author-email: ajamias@redhat.com
Classifier: Environment :: OpenStack
Classifier: Framework :: Django
Classifier: Intended Audience :: Developers
Classifier: Intended Audience :: System Administrators
Classifier: License :: OSI Approved :: Apache Software License
Classifier: Operating System :: POSIX :: Linux
Classifier: Programming Language :: Python
Classifier: Programming Language :: Python :: 3 :: Only
Classifier: Programming Language :: Python :: 3
Classifier: Programming Language :: Python :: 3.6
Classifier: Programming Language :: Python :: 3.7
Classifier: Programming Language :: Python :: 3.8
Classifier: Programming Language :: Python :: 3.9
Classifier: Programming Language :: Python :: 3.10
Classifier: Programming Language :: Python :: 3.11
License-File: LICENSE
License-File: AUTHORS
Requires-Dist: esisdk >=0.5.0
Requires-Dist: horizon >=24.0.0
Requires-Dist: metalsmith >=2.3.0
